prettyconf/__init__.py
prettyconf/casts.py
prettyconf/configuration.py
prettyconf/exceptions.py
prettyconf/loaders.py
prettyconf/parsers.py
prettyconf-2.3.0.dist-info/licenses/AUTHORS.md
prettyconf-2.3.0.dist-info/licenses/LICENSE.txt
prettyconf-2.3.0.dist-info/METADATA
prettyconf-2.3.0.dist-info/WHEEL
prettyconf-2.3.0.dist-info/top_level.txt
prettyconf-2.3.0.dist-info/RECORD
