Metadata-Version: 2.4
Name: prettyconf
Version: 2.3.0
Summary: Separation of settings from code.
Author-email: Osvaldo Santana Neto <prettyconf@osantana.me>
License-Expression: MIT
Project-URL: Source, https://github.com/osantana/prettyconf
Project-URL: Download, https://github.com/osantana/prettyconf/releases
Keywords: asyncio,dispatcher,message,microservices,tasks
Classifier: Development Status :: 5 - Production/Stable
Classifier: Framework :: Django
Classifier: Framework :: Flask
Classifier: Intended Audience :: Developers
Classifier: Natural Language :: English
Classifier: Operating System :: OS Independent
Classifier: Programming Language :: Python :: 3
Classifier: Programming Language :: Python :: 3.10
Classifier: Programming Language :: Python :: 3.11
Classifier: Programming Language :: Python :: 3.12
Classifier: Programming Language :: Python :: 3.13
Classifier: Programming Language :: Python :: 3.9
Classifier: Programming Language :: Python :: Implementation :: PyPy
Classifier: Programming Language :: Python
Classifier: Topic :: Software Development :: Libraries
Requires-Python: >=3.9
License-File: LICENSE.txt
License-File: AUTHORS.md
Provides-Extra: aws
Requires-Dist: boto3<2.0.0,>=1.28.0; extra == "aws"
Dynamic: license-file
